cache.py
config.py
default_prompts.py
main.py
openai_client.py
prompt_builder.py
shell_actions.py
think_actions.py
utils.py
gpt_sh-0.1.3.dist-info/LICENSE
gpt_sh-0.1.3.dist-info/METADATA
gpt_sh-0.1.3.dist-info/WHEEL
gpt_sh-0.1.3.dist-info/entry_points.txt
gpt_sh-0.1.3.dist-info/top_level.txt
gpt_sh-0.1.3.dist-info/RECORD
