Metadata-Version: 2.1
Name: gpt-sh
Version: 0.1.3
Summary: A somewhat more advanced version of Shell GPT
Author: Timo Wang
Author-email: ntwang1994@gmail.com
License: UNKNOWN
Platform: UNKNOWN
License-File: LICENSE
Requires-Dist: shell-gpt
